pysdsim/__init__.py
pysdsim/core.py
pysdsim/handler.py
pysdsim-2025.7.1.dist-info/licenses/LICENSE
pysdsim-2025.7.1.dist-info/METADATA
pysdsim-2025.7.1.dist-info/WHEEL
pysdsim-2025.7.1.dist-info/entry_points.txt
pysdsim-2025.7.1.dist-info/top_level.txt
pysdsim-2025.7.1.dist-info/RECORD
