Metadata-Version: 2.4
Name: pysdsim
Version: 2025.7.1
Summary: An implementation of the Temperature-Dependent Multi-Relaxation Spectroscopic Dielectric Model for thawed and frozen organic soils.
Author-email: Morteza Khazaei <morteza.khazaei@usherbrooke.ca>
License: MIT License
Project-URL: Homepage, https://github.com/Morteza-Khazaei/PySDS
Project-URL: Repository, https://github.com/Morteza-Khazaei/PySDS
Classifier: Programming Language :: Python :: 3
Classifier: Programming Language :: Python :: 3.8
Classifier: Programming Language :: Python :: 3.9
Classifier: Programming Language :: Python :: 3.10
Classifier: Programming Language :: Python :: 3.11
Classifier: License :: OSI Approved :: MIT License
Classifier: Operating System :: OS Independent
Requires-Python: >=3.8
License-File: LICENSE
Requires-Dist: rasterio
Requires-Dist: numpy
Requires-Dist: tables
Requires-Dist: scikit-learn
Requires-Dist: tdmrsdm
Dynamic: license-file
